aex/__init__.py
aex/prior.py
aex-0.0.2.dist-info/METADATA
aex-0.0.2.dist-info/WHEEL
aex-0.0.2.dist-info/top_level.txt
aex-0.0.2.dist-info/RECORD
