Metadata-Version: 2.1
Name: aex
Version: 0.0.2
Summary: Sampling with Blackjax on Aesara
Author-email: Remi Louf <remi@thetypicalset.com>
Project-URL: homepage, https://github.com/rlouf/aex
Project-URL: repository, https://github.com/rlouf/aex
Keywords: probability,machine learning,statistics,mcmc,sampling
Classifier: Development Status :: 5 - Production/Stable
Classifier: Intended Audience :: Developers
Classifier: Intended Audience :: Information Technology
Classifier: Intended Audience :: Science/Research
Classifier: License :: OSI Approved :: Apache Software License
Classifier: Operating System :: MacOS
Classifier: Operating System :: POSIX
Classifier: Programming Language :: Python :: 3.7
Classifier: Programming Language :: Python :: 3.8
Classifier: Programming Language :: Python :: 3.9
Classifier: Programming Language :: Python :: 3.10
Classifier: Topic :: Education
Classifier: Topic :: Scientific/Engineering
Classifier: Topic :: Scientific/Engineering :: Artificial Intelligence
Classifier: Topic :: Scientific/Engineering :: Mathematics
Requires-Python: >=3.7
Requires-Dist: aesara
Requires-Dist: aeppl
Requires-Dist: jax
Requires-Dist: jaxlib
Requires-Dist: blackjax
